LICENSE
MANIFEST.in
README.md
setup.py
cppcloud_web.egg-info/PKG-INFO
cppcloud_web.egg-info/SOURCES.txt
cppcloud_web.egg-info/dependency_links.txt
cppcloud_web.egg-info/entry_points.txt
cppcloud_web.egg-info/not-zip-safe
cppcloud_web.egg-info/requires.txt
cppcloud_web.egg-info/top_level.txt
src/cppcloud_web.py
src/static/about.html
src/static/conf.html
src/static/conf.js
src/static/help.html
src/static/index.html
src/static/jquery-3.3.1.js
src/static/log.html
src/static/log.js
src/static/main.css
src/static/main.html
src/static/main.js
src/static/process.html
src/static/prvd.html
src/static/prvd.js
src/static/setconf.html
src/static/svr.html